scholar/__init__.py
scholar/google_scholar_server.py
scholar/google_scholar_web_search.py
google_scholar_mcp_server-0.1.3.dist-info/METADATA
google_scholar_mcp_server-0.1.3.dist-info/WHEEL
google_scholar_mcp_server-0.1.3.dist-info/entry_points.txt
google_scholar_mcp_server-0.1.3.dist-info/top_level.txt
google_scholar_mcp_server-0.1.3.dist-info/RECORD
