Metadata-Version: 2.4
Name: google-scholar-mcp-server
Version: 0.1.3
Summary: Add your description here
Requires-Python: >=3.13
Requires-Dist: asyncio>=3.4.3
Requires-Dist: bs4>=0.0.2
Requires-Dist: mcp[cli]>=1.5.0
Requires-Dist: requests>=2.32.3
Requires-Dist: scholarly>=1.7.11
